{
  "scenes": [
    {
      "id": "8aa8d080-b995-4892-b718-829dd717612c",
      "name": "MainMenu",
      "systems": [
        {
          "name": "UiBridge",
          "options": {
            "filterComponents": []
          }
        }
      ],
      "levelId": null
    },
    {
      "id": "cd85bb20-d3c0-42e1-840b-d5dc5f09daef",
      "name": "Game",
      "systems": [
        {
          "name": "PhysicsSystem",
          "options": {
            "gravitationalAcceleration": 300
          }
        },
        {
          "name": "CameraSystem",
          "options": {
            "windowNodeId": "root",
            "initialCamera": "585277ec-0325-4b27-8d93-bb5bf97aebaf",
            "scaleSensitivity": 0
          }
        },
        {
          "name": "KeyboardInputSystem",
          "options": {
            "useWindow": true
          }
        },
        {
          "name": "KeyboardControlSystem",
          "options": {}
        },
        {
          "name": "ScenarioSystem",
          "options": {}
        },
        {
          "name": "ScriptSystem",
          "options": {}
        },
        {
          "name": "SpriteRenderer",
          "options": {
            "windowNodeId": "root",
            "backgroundColor": "#000000",
            "backgroundAlpha": 1
          }
        },
        {
          "name": "UiBridge",
          "options": {
            "filterComponents": []
          }
        }
      ],
      "levelId": "814bb481-8226-4f26-8df4-7963417938ec"
    }
  ],
  "levels": [
    {
      "id": "814bb481-8226-4f26-8df4-7963417938ec",
      "name": "Demo Level",
      "actors": [
        {
          "id": "292788ea-cc9d-4270-b851-274479954dbb",
          "name": "Background",
          "components": [
            {
              "name": "Transform",
              "config": {
                "offsetX": 0,
                "offsetY": 0,
                "offsetZ": 0,
                "rotation": 0,
                "scaleX": 1,
                "scaleY": 1
              }
            },
            {
              "name": "Sprite",
              "config": {
                "src": "",
                "width": 480,
                "height": 480,
                "slice": 1,
                "rotation": 0,
                "sortCenter": [
                  0,
                  0
                ],
                "flipX": false,
                "flipY": false,
                "sortingLayer": "background",
                "fit": "stretch",
                "material": {
                  "type": "basic",
                  "options": {
                    "blending": "normal",
                    "color": "#336633",
                    "opacity": 1
                  }
                }
              }
            }
          ],
          "children": []
        },
        {
          "id": "585277ec-0325-4b27-8d93-bb5bf97aebaf",
          "name": "Camera",
          "components": [
            {
              "name": "Transform",
              "config": {
                "offsetX": 0,
                "offsetY": 0,
                "offsetZ": 0,
                "rotation": 0,
                "scaleX": 1,
                "scaleY": 1
              }
            },
            {
              "name": "Camera",
              "config": {
                "zoom": 1
              }
            }
          ],
          "children": []
        },
        {
          "id": "4d86915d-ab2f-4260-9c8b-7f58810c493c",
          "templateId": "d515c668-bdac-424b-92b7-ca62b8b772cc",
          "fromTemplate": true,
          "name": "Enemy Spawner",
          "components": [
            {
              "name": "Transform",
              "config": {
                "offsetX": -228,
                "offsetY": 108,
                "offsetZ": 0,
                "rotation": 0,
                "scaleX": 1,
                "scaleY": 1
              }
            }
          ],
          "children": []
        },
        {
          "id": "11e0501e-9860-478b-8dbb-846d6aa4fd18",
          "templateId": "f14f1694-7865-4783-9b21-774bde2ad9b3",
          "fromTemplate": true,
          "name": "Base",
          "components": [
            {
              "name": "Transform",
              "config": {
                "offsetX": 108,
                "offsetY": -204,
                "offsetZ": 0,
                "rotation": 0,
                "scaleX": 1,
                "scaleY": 1
              }
            }
          ],
          "children": []
        },
        {
          "id": "7c251d5b-cc09-4929-9be9-64e33eceeb3e",
          "templateId": "fb4c3580-ce48-4d24-807c-94956de79311",
          "fromTemplate": true,
          "name": "Track",
          "components": [
            {
              "name": "Transform",
              "config": {
                "offsetX": -132,
                "offsetY": 108,
                "offsetZ": 0,
                "rotation": 0,
                "scaleX": 1,
                "scaleY": 1
              }
            },
            {
              "name": "TrackSegment",
              "config": {
                "index": 0
              }
            }
          ],
          "children": []
        },
        {
          "id": "22584a53-5231-47a0-a305-4929467d2928",
          "templateId": "fb4c3580-ce48-4d24-807c-94956de79311",
          "fromTemplate": true,
          "name": "Track 1",
          "components": [
            {
              "name": "Transform",
              "config": {
                "offsetX": -132,
                "offsetY": -156,
                "offsetZ": 0,
                "rotation": 0,
                "scaleX": 1,
                "scaleY": 1
              }
            },
            {
              "name": "TrackSegment",
              "config": {
                "index": 1
              }
            }
          ],
          "children": []
        },
        {
          "id": "6d8576eb-91da-4d6d-bb60-f6687b0302ac",
          "templateId": "fb4c3580-ce48-4d24-807c-94956de79311",
          "fromTemplate": true,
          "name": "Track 2",
          "components": [
            {
              "name": "Transform",
              "config": {
                "offsetX": -12,
                "offsetY": -156,
                "offsetZ": 0,
                "rotation": 0,
                "scaleX": 1,
                "scaleY": 1
              }
            },
            {
              "name": "TrackSegment",
              "config": {
                "index": 2
              }
            }
          ],
          "children": []
        },
        {
          "id": "d67fd279-3558-4d43-a948-e95523e20d59",
          "templateId": "fb4c3580-ce48-4d24-807c-94956de79311",
          "fromTemplate": true,
          "name": "Track 3",
          "components": [
            {
              "name": "Transform",
              "config": {
                "offsetX": -12,
                "offsetY": 108,
                "offsetZ": 0,
                "rotation": 0,
                "scaleX": 1,
                "scaleY": 1
              }
            },
            {
              "name": "TrackSegment",
              "config": {
                "index": 3
              }
            }
          ],
          "children": []
        },
        {
          "id": "f766ad28-610e-4ec1-aa42-d66f7067b76c",
          "templateId": "fb4c3580-ce48-4d24-807c-94956de79311",
          "fromTemplate": true,
          "name": "Track 4",
          "components": [
            {
              "name": "Transform",
              "config": {
                "offsetX": 108,
                "offsetY": 108,
                "offsetZ": 0,
                "rotation": 0,
                "scaleX": 1,
                "scaleY": 1
              }
            },
            {
              "name": "TrackSegment",
              "config": {
                "index": 4
              }
            }
          ],
          "children": []
        },
        {
          "id": "42c064c3-2e51-4b41-8859-ac0e842e6ba6",
          "templateId": "fb4c3580-ce48-4d24-807c-94956de79311",
          "fromTemplate": true,
          "name": "Track 5",
          "components": [
            {
              "name": "Transform",
              "config": {
                "offsetX": 108,
                "offsetY": -252,
                "offsetZ": 0,
                "rotation": 0,
                "scaleX": 1,
                "scaleY": 1
              }
            },
            {
              "name": "TrackSegment",
              "config": {
                "index": 5
              }
            }
          ],
          "children": []
        }
      ]
    }
  ],
  "templates": [
    {
      "id": "375d21eb-5faf-4e93-b039-dfc8e738ef0e",
      "name": "Enemy",
      "components": [
        {
          "name": "Transform",
          "config": {
            "offsetX": 0,
            "offsetY": 0,
            "offsetZ": 0,
            "rotation": 0,
            "scaleX": 1,
            "scaleY": 1
          }
        },
        {
          "name": "Sprite",
          "config": {
            "src": "",
            "width": 16,
            "height": 16,
            "slice": 1,
            "rotation": 0,
            "sortCenter": [
              0,
              0
            ],
            "flipX": false,
            "flipY": false,
            "sortingLayer": "units",
            "fit": "stretch",
            "material": {
              "type": "basic",
              "options": {
                "blending": "normal",
                "color": "#660000",
                "opacity": 1
              }
            }
          }
        },
        {
          "name": "ColliderContainer",
          "config": {
            "type": "boxCollider",
            "collider": {
              "sizeX": 4,
              "sizeY": 4,
              "centerX": 0,
              "centerY": 0
            }
          }
        },
        {
          "name": "RigidBody",
          "config": {
            "type": "dynamic",
            "mass": 1,
            "useGravity": false,
            "isPermeable": false,
            "ghost": false,
            "drag": 0
          }
        }
      ],
      "children": []
    },
    {
      "id": "f14f1694-7865-4783-9b21-774bde2ad9b3",
      "name": "Base",
      "components": [
        {
          "name": "Transform",
          "config": {
            "offsetX": 0,
            "offsetY": 0,
            "offsetZ": 0,
            "rotation": 0,
            "scaleX": 1,
            "scaleY": 1
          }
        },
        {
          "name": "Sprite",
          "config": {
            "src": "",
            "width": 72,
            "height": 72,
            "slice": 1,
            "rotation": 0,
            "sortCenter": [
              0,
              0
            ],
            "flipX": false,
            "flipY": false,
            "sortingLayer": "",
            "fit": "stretch",
            "material": {
              "type": "basic",
              "options": {
                "blending": "normal",
                "color": "#996633",
                "opacity": 1
              }
            }
          }
        },
        {
          "name": "ColliderContainer",
          "config": {
            "type": "boxCollider",
            "collider": {
              "sizeX": 72,
              "sizeY": 72,
              "centerX": 0,
              "centerY": 0
            }
          }
        }
      ],
      "children": []
    },
    {
      "id": "d515c668-bdac-424b-92b7-ca62b8b772cc",
      "name": "Enemy Spawner",
      "components": [
        {
          "name": "Transform",
          "config": {
            "offsetX": 0,
            "offsetY": 0,
            "offsetZ": 0,
            "rotation": 0,
            "scaleX": 1,
            "scaleY": 1
          }
        },
        {
          "name": "ScriptBundle",
          "config": {
            "scripts": [
              {
                "id": "59e9e449-b3c1-49c9-8662-3635811d46b0",
                "name": "SpawnerScript",
                "options": {
                  "sizeX": 24,
                  "sizeY": 24
                }
              }
            ]
          }
        },
        {
          "name": "Sprite",
          "config": {
            "src": "",
            "width": 24,
            "height": 24,
            "slice": 1,
            "rotation": 0,
            "sortCenter": [
              0,
              0
            ],
            "flipX": false,
            "flipY": false,
            "sortingLayer": "decorations",
            "fit": "stretch",
            "material": {
              "type": "basic",
              "options": {
                "blending": "normal",
                "color": "#ff9900",
                "opacity": 1
              }
            }
          }
        }
      ],
      "children": []
    },
    {
      "id": "fb4c3580-ce48-4d24-807c-94956de79311",
      "name": "Track",
      "components": [
        {
          "name": "Transform",
          "config": {
            "offsetX": 0,
            "offsetY": 0,
            "offsetZ": 0,
            "rotation": 0,
            "scaleX": 1,
            "scaleY": 1
          }
        },
        {
          "name": "Sprite",
          "config": {
            "src": "",
            "width": 24,
            "height": 24,
            "slice": 1,
            "rotation": 0,
            "sortCenter": [
              0,
              0
            ],
            "flipX": false,
            "flipY": false,
            "sortingLayer": "decorations",
            "fit": "stretch",
            "material": {
              "type": "basic",
              "options": {
                "blending": "normal",
                "color": "#333366",
                "opacity": 1
              }
            }
          }
        },
        {
          "name": "ColliderContainer",
          "config": {
            "type": "boxCollider",
            "collider": {
              "sizeX": 24,
              "sizeY": 24,
              "centerX": 0,
              "centerY": 0
            }
          }
        },
        {
          "name": "TrackSegment",
          "config": {
            "index": 0
          }
        }
      ],
      "children": []
    }
  ],
  "loaders": [],
  "globalOptions": [
    {
      "id": "ce9be6d1-0c77-4d9a-9962-228b9dc701af",
      "name": "sortingLayers",
      "type": "array",
      "value": [
        "background",
        "decorations",
        "units"
      ]
    }
  ],
  "startSceneId": "8aa8d080-b995-4892-b718-829dd717612c",
  "startLoaderId": null
}