{
  "scenes": [
    {
      "id": "8aa8d080-b995-4892-b718-829dd717612c",
      "name": "MainMenu",
      "systems": [
        {
          "name": "UiBridge",
          "options": {
            "filterComponents": []
          }
        }
      ],
      "levelId": null
    },
    {
      "id": "cd85bb20-d3c0-42e1-840b-d5dc5f09daef",
      "name": "Game",
      "systems": [
        {
          "name": "MovementSystem",
          "options": {}
        },
        {
          "name": "PhysicsSystem",
          "options": {
            "gravitationalAcceleration": 300
          }
        },
        {
          "name": "CameraSystem",
          "options": {
            "windowNodeId": "root",
            "initialCamera": "585277ec-0325-4b27-8d93-bb5bf97aebaf",
            "scaleSensitivity": 0
          }
        },
        {
          "name": "KeyboardInputSystem",
          "options": {
            "useWindow": true
          }
        },
        {
          "name": "KeyboardControlSystem",
          "options": {}
        },
        {
          "name": "TrackSystem",
          "options": {}
        },
        {
          "name": "ScenarioSystem",
          "options": {}
        },
        {
          "name": "ScriptSystem",
          "options": {}
        },
        {
          "name": "FightSystem",
          "options": {}
        },
        {
          "name": "EffectsSystem",
          "options": {}
        },
        {
          "name": "Reaper",
          "options": {}
        },
        {
          "name": "Animator",
          "options": {}
        },
        {
          "name": "SpriteRenderer",
          "options": {
            "windowNodeId": "root",
            "backgroundColor": "#000000",
            "backgroundAlpha": 1
          }
        },
        {
          "name": "UiBridge",
          "options": {
            "filterComponents": []
          }
        }
      ],
      "levelId": "814bb481-8226-4f26-8df4-7963417938ec"
    }
  ],
  "levels": [
    {
      "id": "814bb481-8226-4f26-8df4-7963417938ec",
      "name": "Demo Level",
      "actors": [
        {
          "id": "292788ea-cc9d-4270-b851-274479954dbb",
          "name": "Background",
          "components": [
            {
              "name": "Transform",
              "config": {
                "offsetX": 0,
                "offsetY": 0,
                "offsetZ": 0,
                "rotation": 0,
                "scaleX": 1,
                "scaleY": 1
              }
            },
            {
              "name": "Sprite",
              "config": {
                "src": "",
                "width": 480,
                "height": 480,
                "slice": 1,
                "rotation": 0,
                "sortCenter": [
                  0,
                  0
                ],
                "flipX": false,
                "flipY": false,
                "sortingLayer": "background",
                "fit": "stretch",
                "material": {
                  "type": "basic",
                  "options": {
                    "blending": "normal",
                    "color": "#99cc66",
                    "opacity": 1
                  }
                }
              }
            }
          ],
          "children": []
        },
        {
          "id": "585277ec-0325-4b27-8d93-bb5bf97aebaf",
          "name": "Player",
          "components": [
            {
              "name": "Transform",
              "config": {
                "offsetX": 0,
                "offsetY": 0,
                "offsetZ": 0,
                "rotation": 0,
                "scaleX": 1,
                "scaleY": 1
              }
            },
            {
              "name": "Camera",
              "config": {
                "zoom": 1
              }
            },
            {
              "name": "Money",
              "config": {
                "value": 200
              }
            },
            {
              "name": "ScriptBundle",
              "config": {
                "scripts": [
                  {
                    "id": "9ee1a559-a98c-4e89-b75d-1dd438aa7205",
                    "name": "PlayerScript",
                    "options": {}
                  }
                ]
              }
            }
          ],
          "children": []
        },
        {
          "id": "4d86915d-ab2f-4260-9c8b-7f58810c493c",
          "templateId": "d515c668-bdac-424b-92b7-ca62b8b772cc",
          "fromTemplate": true,
          "name": "Enemy Spawner",
          "components": [
            {
              "name": "Transform",
              "config": {
                "offsetX": -228,
                "offsetY": 108,
                "offsetZ": 0,
                "rotation": 0,
                "scaleX": 1,
                "scaleY": 1
              }
            }
          ],
          "children": []
        },
        {
          "id": "11e0501e-9860-478b-8dbb-846d6aa4fd18",
          "templateId": "f14f1694-7865-4783-9b21-774bde2ad9b3",
          "fromTemplate": true,
          "name": "Base",
          "components": [
            {
              "name": "Transform",
              "config": {
                "offsetX": 108,
                "offsetY": -204,
                "offsetZ": 0,
                "rotation": 0,
                "scaleX": 1,
                "scaleY": 1
              }
            }
          ],
          "children": []
        },
        {
          "id": "71ffcdb9-1a66-472a-a16c-2998e94e28ae",
          "templateId": "fb4c3580-ce48-4d24-807c-94956de79311",
          "fromTemplate": true,
          "name": "Track 0",
          "components": [
            {
              "name": "Transform",
              "config": {
                "offsetX": -228,
                "offsetY": 108,
                "offsetZ": 0,
                "rotation": 0,
                "scaleX": 1,
                "scaleY": 1
              }
            },
            {
              "name": "TrackSegment",
              "config": {
                "next": [
                  "7c251d5b-cc09-4929-9be9-64e33eceeb3e"
                ]
              }
            }
          ],
          "children": []
        },
        {
          "id": "7c251d5b-cc09-4929-9be9-64e33eceeb3e",
          "templateId": "fb4c3580-ce48-4d24-807c-94956de79311",
          "fromTemplate": true,
          "name": "Track 1",
          "components": [
            {
              "name": "Transform",
              "config": {
                "offsetX": -132,
                "offsetY": 108,
                "offsetZ": 0,
                "rotation": 0,
                "scaleX": 1,
                "scaleY": 1
              }
            },
            {
              "name": "TrackSegment",
              "config": {
                "next": [
                  "22584a53-5231-47a0-a305-4929467d2928",
                  "d67fd279-3558-4d43-a948-e95523e20d59"
                ]
              }
            }
          ],
          "children": []
        },
        {
          "id": "22584a53-5231-47a0-a305-4929467d2928",
          "templateId": "fb4c3580-ce48-4d24-807c-94956de79311",
          "fromTemplate": true,
          "name": "Track 2",
          "components": [
            {
              "name": "Transform",
              "config": {
                "offsetX": -132,
                "offsetY": -156,
                "offsetZ": 0,
                "rotation": 0,
                "scaleX": 1,
                "scaleY": 1
              }
            },
            {
              "name": "TrackSegment",
              "config": {
                "next": [
                  "6d8576eb-91da-4d6d-bb60-f6687b0302ac"
                ]
              }
            }
          ],
          "children": []
        },
        {
          "id": "6d8576eb-91da-4d6d-bb60-f6687b0302ac",
          "templateId": "fb4c3580-ce48-4d24-807c-94956de79311",
          "fromTemplate": true,
          "name": "Track 3",
          "components": [
            {
              "name": "Transform",
              "config": {
                "offsetX": -12,
                "offsetY": -156,
                "offsetZ": 0,
                "rotation": 0,
                "scaleX": 1,
                "scaleY": 1
              }
            },
            {
              "name": "TrackSegment",
              "config": {
                "next": [
                  "d67fd279-3558-4d43-a948-e95523e20d59"
                ]
              }
            }
          ],
          "children": []
        },
        {
          "id": "d67fd279-3558-4d43-a948-e95523e20d59",
          "templateId": "fb4c3580-ce48-4d24-807c-94956de79311",
          "fromTemplate": true,
          "name": "Track 4",
          "components": [
            {
              "name": "Transform",
              "config": {
                "offsetX": -12,
                "offsetY": 108,
                "offsetZ": 0,
                "rotation": 0,
                "scaleX": 1,
                "scaleY": 1
              }
            },
            {
              "name": "TrackSegment",
              "config": {
                "next": [
                  "f766ad28-610e-4ec1-aa42-d66f7067b76c"
                ]
              }
            }
          ],
          "children": []
        },
        {
          "id": "f766ad28-610e-4ec1-aa42-d66f7067b76c",
          "templateId": "fb4c3580-ce48-4d24-807c-94956de79311",
          "fromTemplate": true,
          "name": "Track 5",
          "components": [
            {
              "name": "Transform",
              "config": {
                "offsetX": 108,
                "offsetY": 108,
                "offsetZ": 0,
                "rotation": 0,
                "scaleX": 1,
                "scaleY": 1
              }
            },
            {
              "name": "TrackSegment",
              "config": {
                "next": [
                  "42c064c3-2e51-4b41-8859-ac0e842e6ba6"
                ]
              }
            }
          ],
          "children": []
        },
        {
          "id": "42c064c3-2e51-4b41-8859-ac0e842e6ba6",
          "templateId": "fb4c3580-ce48-4d24-807c-94956de79311",
          "fromTemplate": true,
          "name": "Track 6",
          "components": [
            {
              "name": "Transform",
              "config": {
                "offsetX": 108,
                "offsetY": -252,
                "offsetZ": 0,
                "rotation": 0,
                "scaleX": 1,
                "scaleY": 1
              }
            },
            {
              "name": "TrackSegment",
              "config": {
                "next": [
                  "null"
                ]
              }
            }
          ],
          "children": []
        },
        {
          "id": "889d6ab7-84a3-41dd-a55f-1324e711ace1",
          "name": "Meadow",
          "components": [
            {
              "name": "Sprite",
              "config": {
                "src": "bg-1.png",
                "width": 480,
                "height": 480,
                "slice": 1,
                "rotation": 0,
                "sortCenter": [
                  0,
                  0
                ],
                "flipX": false,
                "flipY": false,
                "sortingLayer": "meadow",
                "fit": "stretch",
                "material": {
                  "type": "basic",
                  "options": {
                    "blending": "normal",
                    "color": "#fff",
                    "opacity": 1
                  }
                }
              }
            },
            {
              "name": "Transform",
              "config": {
                "offsetX": 0,
                "offsetY": 0,
                "offsetZ": 0,
                "rotation": 0,
                "scaleX": 1,
                "scaleY": 1
              }
            }
          ],
          "children": []
        },
        {
          "id": "128e37c1-040d-451d-8d25-0527f6955b27",
          "templateId": "9668d98d-787f-42d0-a738-12924045899b",
          "fromTemplate": true,
          "name": "UI Track Corner Bottom 2",
          "components": [
            {
              "name": "Transform",
              "config": {
                "offsetX": 108,
                "offsetY": 108,
                "offsetZ": 0,
                "rotation": 270,
                "scaleX": 1,
                "scaleY": 1
              }
            }
          ],
          "children": []
        },
        {
          "id": "81794908-fc2a-4371-8b47-ecd7449c2d3c",
          "templateId": "2d33be7b-5184-4b2d-98cd-6119c637ef98",
          "fromTemplate": true,
          "name": "UI Track Corner Top",
          "components": [
            {
              "name": "Transform",
              "config": {
                "offsetX": -132,
                "offsetY": -156,
                "offsetZ": 0,
                "rotation": 0,
                "scaleX": 1,
                "scaleY": 1
              }
            }
          ],
          "children": []
        },
        {
          "id": "031aa2ff-2541-469f-8e18-5828b90c20c0",
          "templateId": "2d33be7b-5184-4b2d-98cd-6119c637ef98",
          "fromTemplate": true,
          "name": "UI Track Corner Top 1",
          "components": [
            {
              "name": "Transform",
              "config": {
                "offsetX": -12,
                "offsetY": -156,
                "offsetZ": 0,
                "rotation": 90,
                "scaleX": 1,
                "scaleY": 1
              }
            }
          ],
          "children": []
        },
        {
          "id": "9a380659-3a75-49cb-8efe-da71c135492e",
          "templateId": "275eebe3-a612-4cfd-9c15-9875c6341f9f",
          "fromTemplate": true,
          "name": "Horizontal Road",
          "components": [
            {
              "name": "Transform",
              "config": {
                "offsetX": -108,
                "offsetY": 108,
                "offsetZ": 0,
                "rotation": 0,
                "scaleX": 1,
                "scaleY": 1
              }
            },
            {
              "name": "Sprite",
              "config": {
                "src": "road/road_h-2.png",
                "width": 216,
                "height": 24,
                "slice": 1,
                "rotation": 0,
                "sortCenter": [
                  0,
                  0
                ],
                "flipX": false,
                "flipY": false,
                "sortingLayer": "decorations",
                "fit": "repeat",
                "material": {
                  "type": "basic",
                  "options": {
                    "blending": "normal",
                    "color": "#fff",
                    "opacity": 1
                  }
                }
              }
            }
          ],
          "children": []
        },
        {
          "id": "d5670adc-6be4-46c0-b9e2-6714c828e0b4",
          "templateId": "9cadb85a-be47-4134-8193-76aa30de0506",
          "fromTemplate": true,
          "name": "Vertical Road",
          "components": [
            {
              "name": "Transform",
              "config": {
                "offsetX": -132,
                "offsetY": -24,
                "offsetZ": 0,
                "rotation": 0,
                "scaleX": 1,
                "scaleY": 1
              }
            },
            {
              "name": "Sprite",
              "config": {
                "src": "road/road_v-2.png",
                "width": 24,
                "height": 240,
                "slice": 1,
                "rotation": 0,
                "sortCenter": [
                  0,
                  0
                ],
                "flipX": false,
                "flipY": false,
                "sortingLayer": "decorations",
                "fit": "repeat",
                "material": {
                  "type": "basic",
                  "options": {
                    "blending": "normal",
                    "color": "#fff",
                    "opacity": 1
                  }
                }
              }
            }
          ],
          "children": []
        },
        {
          "id": "66e80606-5a3a-4f88-8f51-baa7bad48ba5",
          "templateId": "275eebe3-a612-4cfd-9c15-9875c6341f9f",
          "fromTemplate": true,
          "name": "Horizontal Road 1",
          "components": [
            {
              "name": "Transform",
              "config": {
                "offsetX": -72,
                "offsetY": -156,
                "offsetZ": 0,
                "rotation": 0,
                "scaleX": 1,
                "scaleY": 1
              }
            },
            {
              "name": "Sprite",
              "config": {
                "src": "road/road_h-2.png",
                "width": 96,
                "height": 24,
                "slice": 1,
                "rotation": 0,
                "sortCenter": [
                  0,
                  0
                ],
                "flipX": false,
                "flipY": false,
                "sortingLayer": "decorations",
                "fit": "repeat",
                "material": {
                  "type": "basic",
                  "options": {
                    "blending": "normal",
                    "color": "#fff",
                    "opacity": 1
                  }
                }
              }
            }
          ],
          "children": []
        },
        {
          "id": "0e95c755-49e5-4d2c-8c6d-4acdc4d13a99",
          "templateId": "275eebe3-a612-4cfd-9c15-9875c6341f9f",
          "fromTemplate": true,
          "name": "Horizontal Road 2",
          "components": [
            {
              "name": "Transform",
              "config": {
                "offsetX": -108,
                "offsetY": -156,
                "offsetZ": 0,
                "rotation": 0,
                "scaleX": 1,
                "scaleY": 1
              }
            }
          ],
          "children": []
        },
        {
          "id": "122a176f-8350-4bae-8d9e-e7f568eb7129",
          "templateId": "9cadb85a-be47-4134-8193-76aa30de0506",
          "fromTemplate": true,
          "name": "Vertical Road 1",
          "components": [
            {
              "name": "Transform",
              "config": {
                "offsetX": -12,
                "offsetY": -24,
                "offsetZ": 0,
                "rotation": 0,
                "scaleX": 1,
                "scaleY": 1
              }
            },
            {
              "name": "Sprite",
              "config": {
                "src": "road/road_v-1.png",
                "width": 24,
                "height": 240,
                "slice": 1,
                "rotation": 0,
                "sortCenter": [
                  0,
                  0
                ],
                "flipX": false,
                "flipY": false,
                "sortingLayer": "decorations",
                "fit": "repeat",
                "material": {
                  "type": "basic",
                  "options": {
                    "blending": "normal",
                    "color": "#fff",
                    "opacity": 1
                  }
                }
              }
            }
          ],
          "children": []
        },
        {
          "id": "6a8c9431-b21f-41a1-8806-a1e8b6e14abe",
          "templateId": "275eebe3-a612-4cfd-9c15-9875c6341f9f",
          "fromTemplate": true,
          "name": "Horizontal Road copy",
          "components": [
            {
              "name": "Transform",
              "config": {
                "offsetX": 48,
                "offsetY": 108,
                "offsetZ": 0,
                "rotation": 0,
                "scaleX": 1,
                "scaleY": 1
              }
            },
            {
              "name": "Sprite",
              "config": {
                "src": "road/road_h-2.png",
                "width": 96,
                "height": 24,
                "slice": 1,
                "rotation": 0,
                "sortCenter": [
                  0,
                  0
                ],
                "flipX": false,
                "flipY": false,
                "sortingLayer": "decorations",
                "fit": "repeat",
                "material": {
                  "type": "basic",
                  "options": {
                    "blending": "normal",
                    "color": "#fff",
                    "opacity": 1
                  }
                }
              }
            }
          ],
          "children": []
        },
        {
          "id": "7667e5a8-e2ae-4acc-848d-3388632e1760",
          "templateId": "9cadb85a-be47-4134-8193-76aa30de0506",
          "fromTemplate": true,
          "name": "Vertical Road 1 copy",
          "components": [
            {
              "name": "Transform",
              "config": {
                "offsetX": 108,
                "offsetY": -36,
                "offsetZ": 0,
                "rotation": 0,
                "scaleX": 1,
                "scaleY": 1
              }
            },
            {
              "name": "Sprite",
              "config": {
                "src": "road/road_v-1.png",
                "width": 24,
                "height": 264,
                "slice": 1,
                "rotation": 0,
                "sortCenter": [
                  0,
                  0
                ],
                "flipX": false,
                "flipY": false,
                "sortingLayer": "decorations",
                "fit": "repeat",
                "material": {
                  "type": "basic",
                  "options": {
                    "blending": "normal",
                    "color": "#fff",
                    "opacity": 1
                  }
                }
              }
            }
          ],
          "children": []
        },
        {
          "id": "f4cd0806-ff1f-41f6-b066-6dba2f7dcf59",
          "templateId": "11d0673f-ffca-4a71-9b97-1e6326eabf80",
          "fromTemplate": true,
          "name": "Flower Bed",
          "components": [
            {
              "name": "Transform",
              "config": {
                "offsetX": -73,
                "offsetY": -97,
                "offsetZ": 0,
                "rotation": 0,
                "scaleX": 1,
                "scaleY": 1
              }
            }
          ],
          "children": []
        },
        {
          "id": "7d7e9ebe-1c01-45ac-b8b0-00272693d573",
          "templateId": "c6bbd954-f100-412e-9f71-99241a254073",
          "fromTemplate": true,
          "name": "Veg Bed",
          "components": [
            {
              "name": "Transform",
              "config": {
                "offsetX": 47,
                "offsetY": 47,
                "offsetZ": 0,
                "rotation": 0,
                "scaleX": 1,
                "scaleY": 1
              }
            }
          ],
          "children": []
        },
        {
          "id": "3365e057-7131-4326-b228-bb1dc2f90c04",
          "templateId": "12645e38-9f08-419f-8be1-9979a8cdb9ab",
          "fromTemplate": true,
          "name": "Hothouse",
          "components": [
            {
              "name": "Transform",
              "config": {
                "offsetX": 49,
                "offsetY": -34,
                "offsetZ": 0,
                "rotation": 0,
                "scaleX": 1,
                "scaleY": 1
              }
            }
          ],
          "children": []
        },
        {
          "id": "49ee9ecc-7cb3-4f24-bb71-899bec871b2b",
          "templateId": "e54cd27a-e9f5-4f8c-b829-8300f998d504",
          "fromTemplate": true,
          "name": "Construction Spot",
          "components": [
            {
              "name": "Transform",
              "config": {
                "offsetX": -156,
                "offsetY": 60,
                "offsetZ": 0,
                "rotation": 0,
                "scaleX": 1,
                "scaleY": 1
              }
            }
          ],
          "children": []
        },
        {
          "id": "5b2aa601-4aa5-4eb2-aa40-d98d39653e2b",
          "templateId": "e54cd27a-e9f5-4f8c-b829-8300f998d504",
          "fromTemplate": true,
          "name": "Construction Spot 1",
          "components": [
            {
              "name": "Transform",
              "config": {
                "offsetX": -156,
                "offsetY": 36,
                "offsetZ": 0,
                "rotation": 0,
                "scaleX": 1,
                "scaleY": 1
              }
            }
          ],
          "children": []
        },
        {
          "id": "501c164f-66ea-45a5-b0bd-cf4c9a6fc991",
          "templateId": "e54cd27a-e9f5-4f8c-b829-8300f998d504",
          "fromTemplate": true,
          "name": "Construction Spot 2",
          "components": [
            {
              "name": "Transform",
              "config": {
                "offsetX": 12,
                "offsetY": -108,
                "offsetZ": 0,
                "rotation": 0,
                "scaleX": 1,
                "scaleY": 1
              }
            }
          ],
          "children": []
        },
        {
          "id": "b1014fdf-5887-4ac7-a2c2-b3e0550b0ee8",
          "templateId": "e54cd27a-e9f5-4f8c-b829-8300f998d504",
          "fromTemplate": true,
          "name": "Construction Spot 3",
          "components": [
            {
              "name": "Transform",
              "config": {
                "offsetX": 12,
                "offsetY": -132,
                "offsetZ": 0,
                "rotation": 0,
                "scaleX": 1,
                "scaleY": 1
              }
            }
          ],
          "children": []
        },
        {
          "id": "506728b5-6a58-4ddd-8164-733b45c003e3",
          "templateId": "e54cd27a-e9f5-4f8c-b829-8300f998d504",
          "fromTemplate": true,
          "name": "Construction Spot 4",
          "components": [
            {
              "name": "Transform",
              "config": {
                "offsetX": 132,
                "offsetY": -60,
                "offsetZ": 0,
                "rotation": 0,
                "scaleX": 1,
                "scaleY": 1
              }
            }
          ],
          "children": []
        },
        {
          "id": "c3a4f808-4ddd-447c-8056-835cc403ba50",
          "templateId": "e54cd27a-e9f5-4f8c-b829-8300f998d504",
          "fromTemplate": true,
          "name": "Construction Spot 5",
          "components": [
            {
              "name": "Transform",
              "config": {
                "offsetX": 132,
                "offsetY": -36,
                "offsetZ": 0,
                "rotation": 0,
                "scaleX": 1,
                "scaleY": 1
              }
            }
          ],
          "children": []
        },
        {
          "id": "d168ebb7-254f-4827-bcb6-9eb6eb397dce",
          "templateId": "e54cd27a-e9f5-4f8c-b829-8300f998d504",
          "fromTemplate": true,
          "name": "Construction Spot 6",
          "components": [
            {
              "name": "Transform",
              "config": {
                "offsetX": -156,
                "offsetY": 132,
                "offsetZ": 0,
                "rotation": 0,
                "scaleX": 1,
                "scaleY": 1
              }
            }
          ],
          "children": []
        },
        {
          "id": "1584aaeb-a92a-4f09-8683-c064bf475e50",
          "templateId": "e54cd27a-e9f5-4f8c-b829-8300f998d504",
          "fromTemplate": true,
          "name": "Construction Spot 7",
          "components": [
            {
              "name": "Transform",
              "config": {
                "offsetX": -132,
                "offsetY": 132,
                "offsetZ": 0,
                "rotation": 0,
                "scaleX": 1,
                "scaleY": 1
              }
            }
          ],
          "children": []
        },
        {
          "id": "ad576f31-bc69-4767-b536-6f4bdcc6c860",
          "templateId": "e54cd27a-e9f5-4f8c-b829-8300f998d504",
          "fromTemplate": true,
          "name": "Construction Spot 8",
          "components": [
            {
              "name": "Transform",
              "config": {
                "offsetX": -36,
                "offsetY": 132,
                "offsetZ": 0,
                "rotation": 0,
                "scaleX": 1,
                "scaleY": 1
              }
            }
          ],
          "children": []
        },
        {
          "id": "14c03fe1-756a-4aec-bdb0-1ec82c8ebc06",
          "templateId": "e54cd27a-e9f5-4f8c-b829-8300f998d504",
          "fromTemplate": true,
          "name": "Construction Spot 9",
          "components": [
            {
              "name": "Transform",
              "config": {
                "offsetX": -12,
                "offsetY": 132,
                "offsetZ": 0,
                "rotation": 0,
                "scaleX": 1,
                "scaleY": 1
              }
            }
          ],
          "children": []
        },
        {
          "id": "c7a44a2a-f947-474a-832a-cda51d805492",
          "templateId": "e54cd27a-e9f5-4f8c-b829-8300f998d504",
          "fromTemplate": true,
          "name": "Construction Spot 10",
          "components": [
            {
              "name": "Transform",
              "config": {
                "offsetX": -84,
                "offsetY": -180,
                "offsetZ": 0,
                "rotation": 0,
                "scaleX": 1,
                "scaleY": 1
              }
            }
          ],
          "children": []
        },
        {
          "id": "8f881e54-028c-4954-ae64-169010048a81",
          "templateId": "e54cd27a-e9f5-4f8c-b829-8300f998d504",
          "fromTemplate": true,
          "name": "Construction Spot 11",
          "components": [
            {
              "name": "Transform",
              "config": {
                "offsetX": -60,
                "offsetY": -180,
                "offsetZ": 0,
                "rotation": 0,
                "scaleX": 1,
                "scaleY": 1
              }
            }
          ],
          "children": []
        }
      ]
    }
  ],
  "templates": [
    {
      "id": "375d21eb-5faf-4e93-b039-dfc8e738ef0e",
      "name": "Enemy",
      "components": [
        {
          "name": "Transform",
          "config": {
            "offsetX": 0,
            "offsetY": 0,
            "offsetZ": 0,
            "rotation": 0,
            "scaleX": 1,
            "scaleY": 1
          }
        },
        {
          "name": "Sprite",
          "config": {
            "src": "",
            "width": 16,
            "height": 16,
            "slice": 1,
            "rotation": 0,
            "sortCenter": [
              0,
              0
            ],
            "flipX": false,
            "flipY": false,
            "sortingLayer": "units",
            "fit": "stretch",
            "material": {
              "type": "basic",
              "options": {
                "blending": "normal",
                "color": "#660000",
                "opacity": 1
              }
            }
          }
        },
        {
          "name": "ColliderContainer",
          "config": {
            "type": "boxCollider",
            "collider": {
              "sizeX": 4,
              "sizeY": 4,
              "centerX": 0,
              "centerY": 0
            }
          }
        },
        {
          "name": "Movement",
          "config": {
            "speed": 50
          }
        },
        {
          "name": "ViewDirection",
          "config": {
            "x": 0,
            "y": 0
          }
        },
        {
          "name": "Team",
          "config": {
            "index": 1
          }
        },
        {
          "name": "Health",
          "config": {
            "points": 200
          }
        },
        {
          "name": "Animatable",
          "config": {
            "initialState": "1c0ba8c1-d2d2-4619-8409-70c649292ab2",
            "states": [
              {
                "id": "1c0ba8c1-d2d2-4619-8409-70c649292ab2",
                "name": "Idle",
                "type": "individual",
                "speed": 1,
                "timeline": {
                  "frames": [
                    {
                      "id": "2e25f8b5-03db-489f-82c4-cc1d19a594a6",
                      "fields": [
                        {
                          "id": "3f03e974-8bb9-43a1-8dba-0184f376c047",
                          "name": "components.Sprite.currentFrame",
                          "type": "number",
                          "value": 0
                        }
                      ]
                    }
                  ],
                  "looped": false
                },
                "transitions": [
                  {
                    "id": "12e52558-aac8-412b-b601-90174813287a",
                    "state": "f37b563d-f51c-40d7-ab80-3e907d322816",
                    "time": 0,
                    "conditions": [
                      {
                        "id": "ec071914-a90e-44a3-994d-add72fe47568",
                        "type": "event",
                        "props": {
                          "eventType": "Kill"
                        }
                      }
                    ]
                  }
                ]
              },
              {
                "id": "f37b563d-f51c-40d7-ab80-3e907d322816",
                "name": "Death",
                "type": "individual",
                "speed": 1,
                "timeline": {
                  "frames": [
                    {
                      "id": "a9adf487-9d64-4cf2-99d5-8e43f177e77c",
                      "fields": [
                        {
                          "id": "9c61872a-0426-4bbb-b772-e6bf797f04d2",
                          "name": "components.Sprite.disabled",
                          "type": "boolean",
                          "value": true
                        }
                      ]
                    }
                  ],
                  "looped": false
                },
                "transitions": []
              }
            ]
          }
        },
        {
          "name": "ScriptBundle",
          "config": {
            "scripts": [
              {
                "id": "a43be7f8-284f-4cc8-8e2e-563faaf09060",
                "name": "DeathTrackerScript",
                "options": {}
              }
            ]
          }
        }
      ],
      "children": [
        {
          "id": "8cac8689-4f1c-43f4-95b9-5d1bde358d00",
          "name": "Hit Box",
          "components": [
            {
              "name": "Transform",
              "config": {
                "offsetX": 0,
                "offsetY": 0,
                "offsetZ": 0,
                "rotation": 0,
                "scaleX": 1,
                "scaleY": 1
              }
            },
            {
              "name": "HitBox",
              "config": {}
            },
            {
              "name": "ColliderContainer",
              "config": {
                "type": "boxCollider",
                "collider": {
                  "sizeX": 24,
                  "sizeY": 24,
                  "centerX": 0,
                  "centerY": 0
                }
              }
            }
          ],
          "children": []
        }
      ]
    },
    {
      "id": "f14f1694-7865-4783-9b21-774bde2ad9b3",
      "name": "Base",
      "components": [
        {
          "name": "Transform",
          "config": {
            "offsetX": 0,
            "offsetY": 0,
            "offsetZ": 0,
            "rotation": 0,
            "scaleX": 1,
            "scaleY": 1
          }
        },
        {
          "name": "Sprite",
          "config": {
            "src": "house.png",
            "width": 72,
            "height": 72,
            "slice": 1,
            "rotation": 0,
            "sortCenter": [
              0,
              0
            ],
            "flipX": false,
            "flipY": false,
            "sortingLayer": "units",
            "fit": "stretch",
            "material": {
              "type": "basic",
              "options": {
                "blending": "normal",
                "color": "#ffffff",
                "opacity": 1
              }
            }
          }
        },
        {
          "name": "ColliderContainer",
          "config": {
            "type": "boxCollider",
            "collider": {
              "sizeX": 72,
              "sizeY": 72,
              "centerX": 0,
              "centerY": 0
            }
          }
        },
        {
          "name": "ScriptBundle",
          "config": {
            "scripts": [
              {
                "id": "10e7a238-c1a1-4c5b-b2bf-ef258b58e2db",
                "name": "BaseScript",
                "options": {}
              }
            ]
          }
        },
        {
          "name": "Health",
          "config": {
            "points": 100
          }
        }
      ],
      "children": []
    },
    {
      "id": "d515c668-bdac-424b-92b7-ca62b8b772cc",
      "name": "Enemy Spawner",
      "components": [
        {
          "name": "Transform",
          "config": {
            "offsetX": 0,
            "offsetY": 0,
            "offsetZ": 0,
            "rotation": 0,
            "scaleX": 1,
            "scaleY": 1
          }
        },
        {
          "name": "ScriptBundle",
          "config": {
            "scripts": [
              {
                "id": "59e9e449-b3c1-49c9-8662-3635811d46b0",
                "name": "SpawnerScript",
                "options": {
                  "sizeX": 24,
                  "sizeY": 24
                }
              }
            ]
          }
        },
        {
          "name": "Sprite",
          "config": {
            "src": "",
            "width": 24,
            "height": 24,
            "slice": 1,
            "rotation": 0,
            "sortCenter": [
              0,
              0
            ],
            "flipX": false,
            "flipY": false,
            "sortingLayer": "decorations",
            "fit": "stretch",
            "material": {
              "type": "basic",
              "options": {
                "blending": "normal",
                "color": "#ff9900",
                "opacity": 1
              }
            }
          }
        }
      ],
      "children": []
    },
    {
      "id": "fb4c3580-ce48-4d24-807c-94956de79311",
      "name": "Track",
      "components": [
        {
          "name": "Transform",
          "config": {
            "offsetX": 0,
            "offsetY": 0,
            "offsetZ": 0,
            "rotation": 0,
            "scaleX": 1,
            "scaleY": 1
          }
        },
        {
          "name": "Sprite",
          "config": {
            "src": "",
            "width": 24,
            "height": 24,
            "slice": 1,
            "rotation": 0,
            "sortCenter": [
              0,
              0
            ],
            "flipX": false,
            "flipY": false,
            "sortingLayer": "decorations",
            "fit": "stretch",
            "material": {
              "type": "basic",
              "options": {
                "blending": "normal",
                "color": "#333366",
                "opacity": 0
              }
            }
          }
        },
        {
          "name": "TrackSegment",
          "config": {
            "next": []
          }
        }
      ],
      "children": []
    },
    {
      "id": "5d2a2389-144f-4bc9-abf7-2fcdd8f77b5d",
      "name": "Melee Hit",
      "components": [
        {
          "name": "Transform",
          "config": {
            "offsetX": 0,
            "offsetY": 0,
            "offsetZ": 0,
            "rotation": 0,
            "scaleX": 1,
            "scaleY": 1
          }
        },
        {
          "name": "ColliderContainer",
          "config": {
            "type": "boxCollider",
            "collider": {
              "sizeX": 24,
              "sizeY": 24,
              "centerX": 0,
              "centerY": 0
            }
          }
        }
      ],
      "children": []
    },
    {
      "id": "b5ed0a30-1f38-460e-8582-46a776de7afb",
      "name": "Tower",
      "components": [
        {
          "name": "Transform",
          "config": {
            "offsetX": 0,
            "offsetY": 0,
            "offsetZ": 0,
            "rotation": 0,
            "scaleX": 1,
            "scaleY": 1
          }
        },
        {
          "name": "Weapon",
          "config": {
            "type": "range",
            "cooldown": 500,
            "properties": {
              "damage": 50,
              "range": 60,
              "projectileSpeed": 100,
              "projectileRadius": 6,
              "projectileModel": "118dc229-ec6f-44d1-8721-077df5001a2b"
            }
          }
        },
        {
          "name": "ColliderContainer",
          "config": {
            "type": "circleCollider",
            "collider": {
              "centerX": 0,
              "centerY": 0,
              "radius": 60
            }
          }
        },
        {
          "name": "Sprite",
          "config": {
            "src": "",
            "width": 24,
            "height": 24,
            "slice": 1,
            "rotation": 0,
            "sortCenter": [
              0,
              0
            ],
            "flipX": false,
            "flipY": false,
            "sortingLayer": "units",
            "fit": "stretch",
            "material": {
              "type": "basic",
              "options": {
                "blending": "normal",
                "color": "#cccc99",
                "opacity": 1
              }
            }
          }
        },
        {
          "name": "ScriptBundle",
          "config": {
            "scripts": [
              {
                "id": "c39c6831-b48e-48f9-bb01-c96b34d6df13",
                "name": "TowerScript",
                "options": {}
              },
              {
                "id": "bbe192f2-6ada-4352-9ed5-bf7f5dd97fb5",
                "name": "SpotScript",
                "options": {}
              }
            ]
          }
        },
        {
          "name": "ViewDirection",
          "config": {
            "x": 0,
            "y": 0
          }
        },
        {
          "name": "Team",
          "config": {
            "index": 0
          }
        },
        {
          "name": "Tier",
          "config": {
            "index": 0
          }
        }
      ],
      "children": []
    },
    {
      "id": "118dc229-ec6f-44d1-8721-077df5001a2b",
      "name": "Projectile",
      "components": [
        {
          "name": "Transform",
          "config": {
            "offsetX": 0,
            "offsetY": 0,
            "offsetZ": 0,
            "rotation": 0,
            "scaleX": 1,
            "scaleY": 1
          }
        },
        {
          "name": "ColliderContainer",
          "config": {
            "type": "circleCollider",
            "collider": {
              "centerX": 0,
              "centerY": 0,
              "radius": 24
            }
          }
        },
        {
          "name": "Sprite",
          "config": {
            "src": "",
            "width": 12,
            "height": 12,
            "slice": 1,
            "rotation": 0,
            "sortCenter": [
              0,
              0
            ],
            "flipX": false,
            "flipY": false,
            "sortingLayer": "units",
            "fit": "stretch",
            "material": {
              "type": "basic",
              "options": {
                "blending": "normal",
                "color": "#fff",
                "opacity": 1
              }
            }
          }
        },
        {
          "name": "RigidBody",
          "config": {
            "type": "dynamic",
            "mass": 1,
            "useGravity": false,
            "isPermeable": false,
            "ghost": true,
            "drag": 0
          }
        },
        {
          "name": "Animatable",
          "config": {
            "initialState": "22429875-6b28-4f62-8377-0469c33cdb60",
            "states": [
              {
                "id": "22429875-6b28-4f62-8377-0469c33cdb60",
                "name": "Idle",
                "type": "individual",
                "speed": 1,
                "timeline": {
                  "frames": [
                    {
                      "id": "cdf8f10d-bdea-4f44-920d-c6ece1861de3",
                      "fields": [
                        {
                          "id": "a90f32c4-9504-4481-a3c9-3b422624c9ac",
                          "name": "components.Sprite.currentFrame",
                          "type": "number",
                          "value": 0
                        }
                      ]
                    }
                  ],
                  "looped": false
                },
                "transitions": [
                  {
                    "id": "5730e445-4c6d-4885-89fb-3c36edd66431",
                    "state": "a8bf9078-2fbb-4b65-9954-b9956cdc3320",
                    "time": 0,
                    "conditions": [
                      {
                        "id": "8e14d842-c7c0-42b3-80a4-2db06cd1f82f",
                        "type": "event",
                        "props": {
                          "eventType": "Kill"
                        }
                      }
                    ]
                  }
                ]
              },
              {
                "id": "a8bf9078-2fbb-4b65-9954-b9956cdc3320",
                "name": "Death",
                "type": "individual",
                "speed": 1,
                "timeline": {
                  "frames": [
                    {
                      "id": "fe31f2cb-461f-48bc-b65c-3ad61921886c",
                      "fields": [
                        {
                          "id": "016ec7e0-80c7-4155-8cff-c9d21f4fc45c",
                          "name": "components.Sprite.disabled",
                          "type": "boolean",
                          "value": true
                        }
                      ]
                    }
                  ],
                  "looped": false
                },
                "transitions": []
              }
            ]
          }
        }
      ],
      "children": []
    },
    {
      "id": "2d33be7b-5184-4b2d-98cd-6119c637ef98",
      "name": "UI Track Corner Top",
      "components": [
        {
          "name": "Transform",
          "config": {
            "offsetX": 0,
            "offsetY": 0,
            "offsetZ": 0,
            "rotation": 0,
            "scaleX": 1,
            "scaleY": 1
          }
        },
        {
          "name": "Sprite",
          "config": {
            "src": "road/road_c-t.png",
            "width": 24,
            "height": 24,
            "slice": 1,
            "rotation": 0,
            "sortCenter": [
              0,
              0
            ],
            "flipX": false,
            "flipY": false,
            "sortingLayer": "decorations",
            "fit": "stretch",
            "material": {
              "type": "basic",
              "options": {
                "blending": "normal",
                "color": "#fff",
                "opacity": 1
              }
            }
          }
        }
      ]
    },
    {
      "id": "0bd10eee-4ad4-47f9-ba0b-88866efc932f",
      "name": "Tower AoE",
      "components": [
        {
          "name": "Weapon",
          "config": {
            "type": "aoe",
            "cooldown": 500,
            "properties": {
              "damage": 25,
              "range": 60,
              "explosionRadius": 48,
              "explosionModel": "3dbabeaa-7135-4f8a-b3a5-fadeb096c1de",
              "projectileSpeed": 100,
              "projectileRadius": 6,
              "projectileModel": "118dc229-ec6f-44d1-8721-077df5001a2b"
            }
          }
        },
        {
          "name": "ColliderContainer",
          "config": {
            "type": "circleCollider",
            "collider": {
              "centerX": 0,
              "centerY": 0,
              "radius": 60
            }
          }
        },
        {
          "name": "Sprite",
          "config": {
            "src": "",
            "width": 24,
            "height": 24,
            "slice": 1,
            "rotation": 0,
            "sortCenter": [
              0,
              0
            ],
            "flipX": false,
            "flipY": false,
            "sortingLayer": "units",
            "fit": "stretch",
            "material": {
              "type": "basic",
              "options": {
                "blending": "normal",
                "color": "#660033",
                "opacity": 1
              }
            }
          }
        },
        {
          "name": "ScriptBundle",
          "config": {
            "scripts": [
              {
                "id": "c39c6831-b48e-48f9-bb01-c96b34d6df13",
                "name": "TowerScript",
                "options": {}
              },
              {
                "id": "06a9765a-fe30-4fe0-b201-eae8d0042b2c",
                "name": "SpotScript",
                "options": {}
              }
            ]
          }
        },
        {
          "name": "ViewDirection",
          "config": {
            "x": 0,
            "y": 0
          }
        },
        {
          "name": "Team",
          "config": {
            "index": 0
          }
        },
        {
          "name": "Transform",
          "config": {
            "offsetX": 0,
            "offsetY": 0,
            "offsetZ": 0,
            "rotation": 0,
            "scaleX": 1,
            "scaleY": 1
          }
        },
        {
          "name": "Tier",
          "config": {
            "index": 0
          }
        }
      ],
      "children": []
    },
    {
      "id": "3dbabeaa-7135-4f8a-b3a5-fadeb096c1de",
      "name": "Explosion",
      "components": [
        {
          "name": "Sprite",
          "config": {
            "src": "",
            "width": 96,
            "height": 96,
            "slice": 1,
            "rotation": 0,
            "sortCenter": [
              0,
              0
            ],
            "flipX": false,
            "flipY": false,
            "sortingLayer": "units",
            "fit": "stretch",
            "material": {
              "type": "basic",
              "options": {
                "blending": "normal",
                "color": "#fff",
                "opacity": 1
              }
            }
          }
        },
        {
          "name": "Transform",
          "config": {
            "offsetX": 0,
            "offsetY": 0,
            "offsetZ": 0,
            "rotation": 0,
            "scaleX": 1,
            "scaleY": 1
          }
        },
        {
          "name": "ColliderContainer",
          "config": {
            "type": "circleCollider",
            "collider": {
              "centerX": 0,
              "centerY": 0,
              "radius": 48
            }
          }
        },
        {
          "name": "Animatable",
          "config": {
            "initialState": "caf1e25c-493c-47f7-bb2d-e69ad360416f",
            "states": [
              {
                "id": "caf1e25c-493c-47f7-bb2d-e69ad360416f",
                "name": "Idle",
                "type": "individual",
                "speed": 1,
                "timeline": {
                  "frames": [
                    {
                      "id": "d4830788-be6b-4415-8b97-27ef82b22579",
                      "fields": [
                        {
                          "id": "2d136170-fef8-4445-800b-91a3a6674e6d",
                          "name": "components.Sprite.currentFrame",
                          "type": "number",
                          "value": 0
                        }
                      ]
                    }
                  ],
                  "looped": false
                },
                "transitions": [
                  {
                    "id": "6e8c536c-b968-49a2-8d91-f8556052c389",
                    "state": "f3131291-a4d7-4965-8048-9a538888d375",
                    "time": 0,
                    "conditions": [
                      {
                        "id": "cd252b60-c850-44d4-aee5-2838febec60a",
                        "type": "event",
                        "props": {
                          "eventType": "Kill"
                        }
                      }
                    ]
                  }
                ]
              },
              {
                "id": "f3131291-a4d7-4965-8048-9a538888d375",
                "name": "Death",
                "type": "individual",
                "speed": 1,
                "timeline": {
                  "frames": [
                    {
                      "id": "d4830788-be6b-4415-8b97-27ef82b22579",
                      "fields": [
                        {
                          "id": "2d136170-fef8-4445-800b-91a3a6674e6d",
                          "name": "components.Sprite.disabled",
                          "type": "boolean",
                          "value": true
                        }
                      ]
                    }
                  ],
                  "looped": false
                },
                "transitions": []
              }
            ]
          }
        }
      ],
      "children": []
    },
    {
      "id": "9668d98d-787f-42d0-a738-12924045899b",
      "name": "UI Track Corner Bottom",
      "components": [
        {
          "name": "Transform",
          "config": {
            "offsetX": 0,
            "offsetY": 0,
            "offsetZ": 0,
            "rotation": 0,
            "scaleX": 1,
            "scaleY": 1
          }
        },
        {
          "name": "Sprite",
          "config": {
            "src": "road/road_c-b.png",
            "width": 24,
            "height": 24,
            "slice": 1,
            "rotation": 0,
            "sortCenter": [
              0,
              0
            ],
            "flipX": false,
            "flipY": false,
            "sortingLayer": "decorations",
            "fit": "stretch",
            "material": {
              "type": "basic",
              "options": {
                "blending": "normal",
                "color": "#fff",
                "opacity": 1
              }
            }
          }
        }
      ]
    },
    {
      "id": "275eebe3-a612-4cfd-9c15-9875c6341f9f",
      "name": "Horizontal Road",
      "components": [
        {
          "name": "Transform",
          "config": {
            "offsetX": 0,
            "offsetY": 0,
            "offsetZ": 0,
            "rotation": 0,
            "scaleX": 1,
            "scaleY": 1
          }
        },
        {
          "name": "Sprite",
          "config": {
            "src": "road/road_h-1.png",
            "width": 24,
            "height": 24,
            "slice": 1,
            "rotation": 0,
            "sortCenter": [
              0,
              0
            ],
            "flipX": false,
            "flipY": false,
            "sortingLayer": "decorations",
            "fit": "repeat",
            "material": {
              "type": "basic",
              "options": {
                "blending": "normal",
                "color": "#fff",
                "opacity": 1
              }
            }
          }
        }
      ],
      "children": []
    },
    {
      "id": "9cadb85a-be47-4134-8193-76aa30de0506",
      "name": "Vertical Road",
      "components": [
        {
          "name": "Transform",
          "config": {
            "offsetX": 0,
            "offsetY": 0,
            "offsetZ": 0,
            "rotation": 0,
            "scaleX": 1,
            "scaleY": 1
          }
        },
        {
          "name": "Sprite",
          "config": {
            "src": "road/road_v-2.png",
            "width": 24,
            "height": 24,
            "slice": 1,
            "rotation": 0,
            "sortCenter": [
              0,
              0
            ],
            "flipX": false,
            "flipY": false,
            "sortingLayer": "decorations",
            "fit": "repeat",
            "material": {
              "type": "basic",
              "options": {
                "blending": "normal",
                "color": "#fff",
                "opacity": 1
              }
            }
          }
        }
      ],
      "children": []
    },
    {
      "id": "11d0673f-ffca-4a71-9b97-1e6326eabf80",
      "name": "Flower Bed",
      "components": [
        {
          "name": "Transform",
          "config": {
            "offsetX": 0,
            "offsetY": 0,
            "offsetZ": 0,
            "rotation": 0,
            "scaleX": 1,
            "scaleY": 1
          }
        },
        {
          "name": "Sprite",
          "config": {
            "src": "flowers.png",
            "width": 94,
            "height": 94,
            "slice": 1,
            "rotation": 0,
            "sortCenter": [
              0,
              0
            ],
            "flipX": false,
            "flipY": false,
            "sortingLayer": "decorations",
            "fit": "stretch",
            "material": {
              "type": "basic",
              "options": {
                "blending": "normal",
                "color": "#fff",
                "opacity": 1
              }
            }
          }
        }
      ],
      "children": []
    },
    {
      "id": "c6bbd954-f100-412e-9f71-99241a254073",
      "name": "Veg Bed",
      "components": [
        {
          "name": "Transform",
          "config": {
            "offsetX": 0,
            "offsetY": 0,
            "offsetZ": 0,
            "rotation": 0,
            "scaleX": 1,
            "scaleY": 1
          }
        },
        {
          "name": "Sprite",
          "config": {
            "src": "vegs.png",
            "width": 94,
            "height": 94,
            "slice": 1,
            "rotation": 0,
            "sortCenter": [
              0,
              0
            ],
            "flipX": false,
            "flipY": false,
            "sortingLayer": "decorations",
            "fit": "stretch",
            "material": {
              "type": "basic",
              "options": {
                "blending": "normal",
                "color": "#fff",
                "opacity": 1
              }
            }
          }
        }
      ],
      "children": []
    },
    {
      "id": "12645e38-9f08-419f-8be1-9979a8cdb9ab",
      "name": "Hothouse",
      "components": [
        {
          "name": "Transform",
          "config": {
            "offsetX": 0,
            "offsetY": 0,
            "offsetZ": 0,
            "rotation": 0,
            "scaleX": 1,
            "scaleY": 1
          }
        },
        {
          "name": "Sprite",
          "config": {
            "src": "glasshouse.png",
            "width": 72,
            "height": 72,
            "slice": 1,
            "rotation": 0,
            "sortCenter": [
              0,
              0
            ],
            "flipX": false,
            "flipY": false,
            "sortingLayer": "units",
            "fit": "stretch",
            "material": {
              "type": "basic",
              "options": {
                "blending": "normal",
                "color": "#fff",
                "opacity": 1
              }
            }
          }
        }
      ],
      "children": []
    },
    {
      "id": "e28dc035-850c-48cd-872c-b65ac8d6a437",
      "name": "Tower Freeze",
      "components": [
        {
          "name": "Transform",
          "config": {
            "offsetX": 0,
            "offsetY": 0,
            "offsetZ": 0,
            "rotation": 0,
            "scaleX": 1,
            "scaleY": 1
          }
        },
        {
          "name": "Weapon",
          "config": {
            "type": "freeze",
            "cooldown": 500,
            "properties": {
              "damage": 10,
              "range": 60,
              "explosionRadius": 48,
              "explosionModel": "3dbabeaa-7135-4f8a-b3a5-fadeb096c1de",
              "projectileSpeed": 100,
              "projectileRadius": 6,
              "projectileModel": "118dc229-ec6f-44d1-8721-077df5001a2b",
              "slowFactor": 0.5
            }
          }
        },
        {
          "name": "ColliderContainer",
          "config": {
            "type": "circleCollider",
            "collider": {
              "centerX": 0,
              "centerY": 0,
              "radius": 60
            }
          }
        },
        {
          "name": "Sprite",
          "config": {
            "src": "",
            "width": 24,
            "height": 24,
            "slice": 1,
            "rotation": 0,
            "sortCenter": [
              0,
              0
            ],
            "flipX": false,
            "flipY": false,
            "sortingLayer": "units",
            "fit": "stretch",
            "material": {
              "type": "basic",
              "options": {
                "blending": "normal",
                "color": "#669999",
                "opacity": 1
              }
            }
          }
        },
        {
          "name": "ScriptBundle",
          "config": {
            "scripts": [
              {
                "id": "c39c6831-b48e-48f9-bb01-c96b34d6df13",
                "name": "TowerScript",
                "options": {}
              },
              {
                "id": "70aae907-6304-4f31-ba8f-dfcb2d043cbf",
                "name": "SpotScript",
                "options": {}
              }
            ]
          }
        },
        {
          "name": "ViewDirection",
          "config": {
            "x": 0,
            "y": 0
          }
        },
        {
          "name": "Team",
          "config": {
            "index": 0
          }
        },
        {
          "name": "Tier",
          "config": {
            "index": 0
          }
        }
      ],
      "children": []
    },
    {
      "id": "928f5cb7-263b-48dd-8e79-74b769c18dbc",
      "name": "Freeze Effect",
      "components": [
        {
          "name": "Transform",
          "config": {
            "offsetX": 0,
            "offsetY": 0,
            "offsetZ": 0,
            "rotation": 0,
            "scaleX": 1,
            "scaleY": 1
          }
        },
        {
          "name": "Effect",
          "config": {
            "type": "timeLimited",
            "applicatorOptions": {
              "duration": 1000
            },
            "script": "freeze"
          }
        }
      ],
      "children": []
    },
    {
      "id": "e54cd27a-e9f5-4f8c-b829-8300f998d504",
      "name": "Construction Spot",
      "components": [
        {
          "name": "Transform",
          "config": {
            "offsetX": 0,
            "offsetY": 0,
            "offsetZ": 0,
            "rotation": 0,
            "scaleX": 1,
            "scaleY": 1
          }
        },
        {
          "name": "Sprite",
          "config": {
            "src": "construction-spot.png",
            "width": 24,
            "height": 24,
            "slice": 1,
            "rotation": 0,
            "sortCenter": [
              0,
              0
            ],
            "flipX": false,
            "flipY": false,
            "sortingLayer": "decorations",
            "fit": "stretch",
            "material": {
              "type": "basic",
              "options": {
                "blending": "normal",
                "color": "#fff",
                "opacity": 1
              }
            }
          }
        },
        {
          "name": "ScriptBundle",
          "config": {
            "scripts": [
              {
                "id": "52ec317c-4d57-41da-bb58-b857181c0952",
                "name": "SpotScript",
                "options": {}
              }
            ]
          }
        }
      ],
      "children": []
    },
    {
      "id": "742dd0f0-ee58-4680-b858-d8d61afa0c2d",
      "name": "Tower Selection",
      "components": [
        {
          "name": "Sprite",
          "config": {
            "src": "selection.png",
            "width": 28,
            "height": 28,
            "slice": 1,
            "rotation": 0,
            "sortCenter": [
              0,
              0
            ],
            "flipX": false,
            "flipY": false,
            "sortingLayer": "units",
            "fit": "stretch",
            "material": {
              "type": "basic",
              "options": {
                "blending": "normal",
                "color": "#fff",
                "opacity": 1
              }
            }
          }
        },
        {
          "name": "Transform",
          "config": {
            "offsetX": 0,
            "offsetY": 0,
            "offsetZ": 0,
            "rotation": 0,
            "scaleX": 1,
            "scaleY": 1
          }
        }
      ],
      "children": []
    }
  ],
  "loaders": [],
  "globalOptions": [
    {
      "id": "ce9be6d1-0c77-4d9a-9962-228b9dc701af",
      "name": "sortingLayers",
      "type": "array",
      "value": [
        "background",
        "meadow",
        "decorations",
        "units"
      ]
    }
  ],
  "startSceneId": "8aa8d080-b995-4892-b718-829dd717612c",
  "startLoaderId": null
}